<?xml version="1.0" encoding="UTF-8"?>
<beans xmlns="http://www.springframework.org/schema/beans"
	xmlns:xsi="http://www.w3.org/2001/XMLSchema-instance"
	xmlns:mybatis-spring="http://mybatis.org/schema/mybatis-spring"
	xsi:schemaLocation="http://mybatis.org/schema/mybatis-spring http://mybatis.org/schema/mybatis-spring-1.2.xsd
		http://www.springframework.org/schema/beans https://www.springframework.org/schema/beans/spring-beans.xsd">

	<!-- Root Context: defines shared resources visible to all other web components -->
	<bean id="nateDBCP" class="com.zaxxer.hikari.HikariConfig">
		<property name="driverClassName"
			value="oracle.jdbc.driver.OracleDriver"></property>
		<property name="jdbcUrl"
			value="jdbc:oracle:thin:@192.168.0.139:1521:xe"></property>
		<property name="username" value="NATECHILDREN"></property>
		<property name="password" value="1234"></property>
	</bean>

	<bean id="nateDS" class="com.zaxxer.hikari.HikariDataSource"
		destroy-method="close">
		<constructor-arg ref="nateDBCP"></constructor-arg>
	</bean>
	<bean id="nateSessionFactory"
		class="org.mybatis.spring.SqlSessionFactoryBean">
		<property name="dataSource" ref="nateDS"></property>
	</bean>
	<bean id="txManager"
		class="org.springframework.jdbc.datasource.DataSourceTransactionManager">
		<property name="dataSource" ref="nateDS"></property>
	</bean>
	<mybatis-spring:scan base-package="icia.escape.db" />
	
	<!-- JAVA SEND MAIL -->
	<bean id="javaMail" class="org.springframework.mail.javamail.JavaMailSenderImpl">
      <property name = "host" value="smtp.naver.com"/>
      <property name = "port" value="587"/>
      <property name = "username" value="secuandb4"/>
      <property name = "password" value="dbgksehd9713"/>
      <property name = "defaultEncoding" value="utf-8"/>
      <property name = "javaMailProperties">
         <props>
            <prop key="mail.debug">true</prop>
            <prop key="mail.transport.protocol">smtp</prop>
            <prop key="mail.smtp.starttls.enable">true</prop>
            <prop key="mail.smtp.ssl.checkserveridentity">true</prop>
            <prop key="mail.smtp.auth">true</prop>
            <prop key="mail.smtps.ssl.trust">*</prop>
            <prop key="mail.smtp.socketFactory.class">javax.net.ssl.SSLSocketFactory</prop>
         </props>

         </property>  
      </bean>
</beans>


